pocketlint/__init__.py
pocketlint/pangocheck.py
pocketlint/translatepo.py
pocketlint/checkers/__init__.py
pocketlint/checkers/environ.py
pocketlint/checkers/intl.py
pocketlint/checkers/markup.py
pocketlint/checkers/pointless-override.py
pocketlint/checkers/preconf.py
pocketlint-0.26.dist-info/licenses/COPYING
pocketlint-0.26.dist-info/METADATA
pocketlint-0.26.dist-info/WHEEL
pocketlint-0.26.dist-info/top_level.txt
pocketlint-0.26.dist-info/RECORD
