Metadata-Version: 2.4
Name: pocketlint
Version: 0.26
Summary: Support for running pylint against projects
Author-email: Chris Lumens <clumens@redhat.com>
Maintainer-email: Jiri Konecny <jkonecny@redhat.com>, Vojtech Trefny <vtrefny@redhat.com>
License:                     GNU GENERAL PUBLIC LICENSE
Project-URL: source, https://github.com/rhinstaller/pocketlint
Classifier: Programming Language :: Python :: 3
Classifier: License :: OSI Approved :: GNU General Public License (GPL)
Classifier: Operating System :: OS Independent
Classifier: Topic :: Software Development :: Testing
License-File: COPYING
Requires-Dist: pylint
Requires-Dist: polib
Requires-Dist: packaging
Dynamic: license-file
